bulk_upload_testrail/__init__.py
bulk_upload_testrail/update_report.py
bulk_upload_testrail/upload_report.py
bulk_upload_testrail-0.1.3.dist-info/METADATA
bulk_upload_testrail-0.1.3.dist-info/WHEEL
bulk_upload_testrail-0.1.3.dist-info/top_level.txt
bulk_upload_testrail-0.1.3.dist-info/RECORD
