Metadata-Version: 2.1
Name: bulk_upload_testrail
Version: 0.1.3
Summary: A simple Python library for bulk upload to testrail in robot framework.
Author: Adi Darmawan
